fxvol/__init__.py
fxvol/lee_extrapolation_helper.py
fxvol/marketdata_helper.py
fxvol/plot_helper.py
fxvol-0.1.dist-info/DESCRIPTION.rst
fxvol-0.1.dist-info/METADATA
fxvol-0.1.dist-info/RECORD
fxvol-0.1.dist-info/WHEEL
fxvol-0.1.dist-info/metadata.json
fxvol-0.1.dist-info/top_level.txt
