Metadata-Version: 2.0
Name: fxvol
Version: 0.1
Summary: poc in python for Lee extrapolation
Home-page: UNKNOWN
Author: Jerome Petit
Author-email: jerome.petit@misys.com
License: UNKNOWN
Platform: UNKNOWN
Classifier: Programming Language :: Python :: 3
Classifier: License :: OSI Approved :: MIT License
Classifier: Operating System :: OS Independent
